[
 {
   "Rank": 1,
   "SeasonGame": null,
   "Date": "2003-10-28",
   "Age": "25-066",
   "Team": "LAL",
   "FIELD6": "",
   "Opponent": "DAL",
   "FIELD8": "W (+16)",
   "GamesStarted": "Did Not Dress",
   "MinsPlayed": "",
   "FieldGoals": null,
   "FieldGoalsAttempted": null,
   "FieldGoalPercentage": null,
   "ThreePointFieldGoals": null,
   "ThreePointFieldGoalAttempted": null,
   "ThreePointFieldGoalPercentage": null,
   "FreeThrows": null,
   "FreeThrowAttempts": null,
   "FreeThrowPercentage": null,
   "OffensiveRebounds": null,
   "DeffensiveRebounds": null,
   "TotalRebounds": null,
   "Assists": null,
   "Steals": null,
   "Blocks": null,
   "Turnovers": null,
   "PersonalFouls": null,
   "Points": null,
   "GameScore": null,
   "+": {
      "-": null
   }
},
 {
   "Rank": 2,
   "SeasonGame": 1,
   "Date": "2003-11-01",
   "Age": "25-070",
   "Team": "LAL",
   "FIELD6": "@",
   "Opponent": "PHO",
   "FIELD8": "W (+4)",
   "GamesStarted": "1",
   "MinsPlayed": "36:30:00",
   "FieldGoals": 4,
   "FieldGoalsAttempted": 12,
   "FieldGoalPercentage": 0.333,
   "ThreePointFieldGoals": 0,
   "ThreePointFieldGoalAttempted": 1,
   "ThreePointFieldGoalPercentage": 0,
   "FreeThrows": 7,
   "FreeThrowAttempts": 10,
   "FreeThrowPercentage": 0.7,
   "OffensiveRebounds": 0,
   "DeffensiveRebounds": 6,
   "TotalRebounds": 6,
   "Assists": 4,
   "Steals": 0,
   "Blocks": 1,
   "Turnovers": 2,
   "PersonalFouls": 4,
   "Points": 15,
   "GameScore": 8.7,
   "+": {
      "-": -3
   }
},
 {
   "Rank": 3,
   "SeasonGame": 2,
   "Date": "2003-11-02",
   "Age": "25-071",
   "Team": "LAL",
   "FIELD6": "",
   "Opponent": "GSW",
   "FIELD8": "W (+15)",
   "GamesStarted": "1",
   "MinsPlayed": "35:03:00",
   "FieldGoals": 7,
   "FieldGoalsAttempted": 12,
   "FieldGoalPercentage": 0.583,
   "ThreePointFieldGoals": 2,
   "ThreePointFieldGoalAttempted": 3,
   "ThreePointFieldGoalPercentage": 0.667,
   "FreeThrows": 5,
   "FreeThrowAttempts": 5,
   "FreeThrowPercentage": 1,
   "OffensiveRebounds": 1,
   "DeffensiveRebounds": 3,
   "TotalRebounds": 4,
   "Assists": 2,
   "Steals": 5,
   "Blocks": 1,
   "Turnovers": 4,
   "PersonalFouls": 4,
   "Points": 21,
   "GameScore": 18.5,
   "+": {
      "-": 13
   }
},
 {
   "Rank": 4,
   "SeasonGame": 3,
   "Date": "2003-11-04",
   "Age": "25-073",
   "Team": "LAL",
   "FIELD6": "@",
   "Opponent": "MIL",
   "FIELD8": "W (+6)",
   "GamesStarted": "1",
   "MinsPlayed": "40:22:00",
   "FieldGoals": 10,
   "FieldGoalsAttempted": 22,
   "FieldGoalPercentage": 0.455,
   "ThreePointFieldGoals": 2,
   "ThreePointFieldGoalAttempted": 4,
   "ThreePointFieldGoalPercentage": 0.5,
   "FreeThrows": 9,
   "FreeThrowAttempts": 10,
   "FreeThrowPercentage": 0.9,
   "OffensiveRebounds": 5,
   "DeffensiveRebounds": 2,
   "TotalRebounds": 7,
   "Assists": 8,
   "Steals": 1,
   "Blocks": 2,
   "Turnovers": 0,
   "PersonalFouls": 3,
   "Points": 31,
   "GameScore": 30.1,
   "+": {
      "-": 7
   }
},
 {
   "Rank": 5,
   "SeasonGame": 4,
   "Date": "2003-11-06",
   "Age": "25-075",
   "Team": "LAL",
   "FIELD6": "@",
   "Opponent": "SAS",
   "FIELD8": "W (+3)",
   "GamesStarted": "1",
   "MinsPlayed": "48:56:00",
   "FieldGoals": 16,
   "FieldGoalsAttempted": 29,
   "FieldGoalPercentage": 0.552,
   "ThreePointFieldGoals": 1,
   "ThreePointFieldGoalAttempted": 4,
   "ThreePointFieldGoalPercentage": 0.25,
   "FreeThrows": 4,
   "FreeThrowAttempts": 5,
   "FreeThrowPercentage": 0.8,
   "OffensiveRebounds": 2,
   "DeffensiveRebounds": 3,
   "TotalRebounds": 5,
   "Assists": 2,
   "Steals": 4,
   "Blocks": 0,
   "Turnovers": 2,
   "PersonalFouls": 4,
   "Points": 37,
   "GameScore": 26.8,
   "+": {
      "-": 4
   }
},
 {
   "Rank": 6,
   "SeasonGame": 5,
   "Date": "2003-11-07",
   "Age": "25-076",
   "Team": "LAL",
   "FIELD6": "@",
   "Opponent": "NOH",
   "FIELD8": "L (-19)",
   "GamesStarted": "1",
   "MinsPlayed": "36:58:00",
   "FieldGoals": 4,
   "FieldGoalsAttempted": 14,
   "FieldGoalPercentage": 0.286,
   "ThreePointFieldGoals": 0,
   "ThreePointFieldGoalAttempted": 4,
   "ThreePointFieldGoalPercentage": 0,
   "FreeThrows": 3,
   "FreeThrowAttempts": 4,
   "FreeThrowPercentage": 0.75,
   "OffensiveRebounds": 1,
   "DeffensiveRebounds": 3,
   "TotalRebounds": 4,
   "Assists": 3,
   "Steals": 1,
   "Blocks": 0,
   "Turnovers": 3,
   "PersonalFouls": 3,
   "Points": 11,
   "GameScore": 2.9,
   "+": {
      "-": -24
   }
},
 {
   "Rank": 7,
   "SeasonGame": 6,
   "Date": "2003-11-10",
   "Age": "25-079",
   "Team": "LAL",
   "FIELD6": "@",
   "Opponent": "MEM",
   "FIELD8": "L (-10)",
   "GamesStarted": "1",
   "MinsPlayed": "33:22:00",
   "FieldGoals": 5,
   "FieldGoalsAttempted": 15,
   "FieldGoalPercentage": 0.333,
   "ThreePointFieldGoals": 0,
   "ThreePointFieldGoalAttempted": 2,
   "ThreePointFieldGoalPercentage": 0,
   "FreeThrows": 9,
   "FreeThrowAttempts": 10,
   "FreeThrowPercentage": 0.9,
   "OffensiveRebounds": 1,
   "DeffensiveRebounds": 3,
   "TotalRebounds": 4,
   "Assists": 5,
   "Steals": 2,
   "Blocks": 0,
   "Turnovers": 6,
   "PersonalFouls": 4,
   "Points": 19,
   "GameScore": 9.6,
   "+": {
      "-": -3
   }
},
 {
   "Rank": 8,
   "SeasonGame": 7,
   "Date": "2003-11-12",
   "Age": "25-081",
   "Team": "LAL",
   "FIELD6": "",
   "Opponent": "TOR",
   "FIELD8": "W (+15)",
   "GamesStarted": "1",
   "MinsPlayed": "37:05:00",
   "FieldGoals": 5,
   "FieldGoalsAttempted": 11,
   "FieldGoalPercentage": 0.455,
   "ThreePointFieldGoals": 1,
   "ThreePointFieldGoalAttempted": 1,
   "ThreePointFieldGoalPercentage": 1,
   "FreeThrows": 8,
   "FreeThrowAttempts": 10,
   "FreeThrowPercentage": 0.8,
   "OffensiveRebounds": 1,
   "DeffensiveRebounds": 2,
   "TotalRebounds": 3,
   "Assists": 4,
   "Steals": 1,
   "Blocks": 0,
   "Turnovers": 3,
   "PersonalFouls": 4,
   "Points": 19,
   "GameScore": 13,
   "+": {
      "-": 1
   }
},
 {
   "Rank": 9,
   "SeasonGame": 8,
   "Date": "2003-11-14",
   "Age": "25-083",
   "Team": "LAL",
   "FIELD6": "",
   "Opponent": "DET",
   "FIELD8": "W (+5)",
   "GamesStarted": "1",
   "MinsPlayed": "37:27:00",
   "FieldGoals": 6,
   "FieldGoalsAttempted": 11,
   "FieldGoalPercentage": 0.545,
   "ThreePointFieldGoals": 0,
   "ThreePointFieldGoalAttempted": 0,
   "ThreePointFieldGoalPercentage": null,
   "FreeThrows": 4,
   "FreeThrowAttempts": 4,
   "FreeThrowPercentage": 1,
   "OffensiveRebounds": 0,
   "DeffensiveRebounds": 3,
   "TotalRebounds": 3,
   "Assists": 1,
   "Steals": 3,
   "Blocks": 2,
   "Turnovers": 1,
   "PersonalFouls": 5,
   "Points": 16,
   "GameScore": 13.7,
   "+": {
      "-": 12
   }
},
 {
   "Rank": 10,
   "SeasonGame": 9,
   "Date": "2003-11-16",
   "Age": "25-085",
   "Team": "LAL",
   "FIELD6": "",
   "Opponent": "MIA",
   "FIELD8": "W (+22)",
   "GamesStarted": "1",
   "MinsPlayed": "32:53:00",
   "FieldGoals": 6,
   "FieldGoalsAttempted": 10,
   "FieldGoalPercentage": 0.6,
   "ThreePointFieldGoals": 0,
   "ThreePointFieldGoalAttempted": 1,
   "ThreePointFieldGoalPercentage": 0,
   "FreeThrows": 15,
   "FreeThrowAttempts": 16,
   "FreeThrowPercentage": 0.938,
   "OffensiveRebounds": 1,
   "DeffensiveRebounds": 3,
   "TotalRebounds": 4,
   "Assists": 6,
   "Steals": 2,
   "Blocks": 0,
   "Turnovers": 3,
   "PersonalFouls": 2,
   "Points": 27,
   "GameScore": 26,
   "+": {
      "-": 21
   }
},
 {
   "Rank": 11,
   "SeasonGame": 10,
   "Date": "2003-11-18",
   "Age": "25-087",
   "Team": "LAL",
   "FIELD6": "@",
   "Opponent": "DET",
   "FIELD8": "L (-10)",
   "GamesStarted": "1",
   "MinsPlayed": "40:45:00",
   "FieldGoals": 4,
   "FieldGoalsAttempted": 14,
   "FieldGoalPercentage": 0.286,
   "ThreePointFieldGoals": 0,
   "ThreePointFieldGoalAttempted": 2,
   "ThreePointFieldGoalPercentage": 0,
   "FreeThrows": 11,
   "FreeThrowAttempts": 11,
   "FreeThrowPercentage": 1,
   "OffensiveRebounds": 1,
   "DeffensiveRebounds": 1,
   "TotalRebounds": 2,
   "Assists": 3,
   "Steals": 0,
   "Blocks": 0,
   "Turnovers": 0,
   "PersonalFouls": 3,
   "Points": 19,
   "GameScore": 12.7,
   "+": {
      "-": -9
   }
},
 {
   "Rank": 12,
   "SeasonGame": 11,
   "Date": "2003-11-19",
   "Age": "25-088",
   "Team": "LAL",
   "FIELD6": "@",
   "Opponent": "NYK",
   "FIELD8": "W (+21)",
   "GamesStarted": "1",
   "MinsPlayed": "33:42:00",
   "FieldGoals": 7,
   "FieldGoalsAttempted": 13,
   "FieldGoalPercentage": 0.538,
   "ThreePointFieldGoals": 0,
   "ThreePointFieldGoalAttempted": 0,
   "ThreePointFieldGoalPercentage": null,
   "FreeThrows": 7,
   "FreeThrowAttempts": 9,
   "FreeThrowPercentage": 0.778,
   "OffensiveRebounds": 1,
   "DeffensiveRebounds": 1,
   "TotalRebounds": 2,
   "Assists": 4,
   "Steals": 1,
   "Blocks": 0,
   "Turnovers": 1,
   "PersonalFouls": 5,
   "Points": 21,
   "GameScore": 15.7,
   "+": {
      "-": 17
   }
},
 {
   "Rank": 13,
   "SeasonGame": 12,
   "Date": "2003-11-21",
   "Age": "25-090",
   "Team": "LAL",
   "FIELD6": "",
   "Opponent": "CHI",
   "FIELD8": "W (+7)",
   "GamesStarted": "1",
   "MinsPlayed": "36:50:00",
   "FieldGoals": 10,
   "FieldGoalsAttempted": 19,
   "FieldGoalPercentage": 0.526,
   "ThreePointFieldGoals": 0,
   "ThreePointFieldGoalAttempted": 1,
   "ThreePointFieldGoalPercentage": 0,
   "FreeThrows": 8,
   "FreeThrowAttempts": 11,
   "FreeThrowPercentage": 0.727,
   "OffensiveRebounds": 1,
   "DeffensiveRebounds": 4,
   "TotalRebounds": 5,
   "Assists": 4,
   "Steals": 3,
   "Blocks": 1,
   "Turnovers": 3,
   "PersonalFouls": 4,
   "Points": 28,
   "GameScore": 21.3,
   "+": {
      "-": 16
   }
},
 {
   "Rank": 14,
   "SeasonGame": 13,
   "Date": "2003-11-23",
   "Age": "25-092",
   "Team": "LAL",
   "FIELD6": "",
   "Opponent": "MEM",
   "FIELD8": "W (+32)",
   "GamesStarted": "1",
   "MinsPlayed": "31:37:00",
   "FieldGoals": 8,
   "FieldGoalsAttempted": 16,
   "FieldGoalPercentage": 0.5,
   "ThreePointFieldGoals": 1,
   "ThreePointFieldGoalAttempted": 2,
   "ThreePointFieldGoalPercentage": 0.5,
   "FreeThrows": 11,
   "FreeThrowAttempts": 12,
   "FreeThrowPercentage": 0.917,
   "OffensiveRebounds": 1,
   "DeffensiveRebounds": 2,
   "TotalRebounds": 3,
   "Assists": 3,
   "Steals": 4,
   "Blocks": 0,
   "Turnovers": 1,
   "PersonalFouls": 2,
   "Points": 28,
   "GameScore": 25.2,
   "+": {
      "-": 20
   }
},
 {
   "Rank": 15,
   "SeasonGame": 14,
   "Date": "2003-11-26",
   "Age": "25-095",
   "Team": "LAL",
   "FIELD6": "",
   "Opponent": "WAS",
   "FIELD8": "W (+21)",
   "GamesStarted": "1",
   "MinsPlayed": "25:29:00",
   "FieldGoals": 7,
   "FieldGoalsAttempted": 13,
   "FieldGoalPercentage": 0.538,
   "ThreePointFieldGoals": 1,
   "ThreePointFieldGoalAttempted": 3,
   "ThreePointFieldGoalPercentage": 0.333,
   "FreeThrows": 7,
   "FreeThrowAttempts": 7,
   "FreeThrowPercentage": 1,
   "OffensiveRebounds": 0,
   "DeffensiveRebounds": 4,
   "TotalRebounds": 4,
   "Assists": 4,
   "Steals": 2,
   "Blocks": 0,
   "Turnovers": 3,
   "PersonalFouls": 3,
   "Points": 22,
   "GameScore": 17.5,
   "+": {
      "-": 15
   }
},
 {
   "Rank": 16,
   "SeasonGame": 15,
   "Date": "2003-11-28",
   "Age": "25-097",
   "Team": "LAL",
   "FIELD6": "",
   "Opponent": "SAS",
   "FIELD8": "W (+16)",
   "GamesStarted": "1",
   "MinsPlayed": "30:47:00",
   "FieldGoals": 6,
   "FieldGoalsAttempted": 13,
   "FieldGoalPercentage": 0.462,
   "ThreePointFieldGoals": 1,
   "ThreePointFieldGoalAttempted": 2,
   "ThreePointFieldGoalPercentage": 0.5,
   "FreeThrows": 4,
   "FreeThrowAttempts": 6,
   "FreeThrowPercentage": 0.667,
   "OffensiveRebounds": 0,
   "DeffensiveRebounds": 2,
   "TotalRebounds": 2,
   "Assists": 2,
   "Steals": 1,
   "Blocks": 0,
   "Turnovers": 0,
   "PersonalFouls": 0,
   "Points": 17,
   "GameScore": 12.5,
   "+": {
      "-": 24
   }
},
 {
   "Rank": 17,
   "SeasonGame": 16,
   "Date": "2003-11-30",
   "Age": "25-099",
   "Team": "LAL",
   "FIELD6": "",
   "Opponent": "IND",
   "FIELD8": "W (+22)",
   "GamesStarted": "1",
   "MinsPlayed": "35:35:00",
   "FieldGoals": 4,
   "FieldGoalsAttempted": 10,
   "FieldGoalPercentage": 0.4,
   "ThreePointFieldGoals": 1,
   "ThreePointFieldGoalAttempted": 2,
   "ThreePointFieldGoalPercentage": 0.5,
   "FreeThrows": 3,
   "FreeThrowAttempts": 4,
   "FreeThrowPercentage": 0.75,
   "OffensiveRebounds": 1,
   "DeffensiveRebounds": 1,
   "TotalRebounds": 2,
   "Assists": 7,
   "Steals": 1,
   "Blocks": 0,
   "Turnovers": 2,
   "PersonalFouls": 3,
   "Points": 12,
   "GameScore": 9.9,
   "+": {
      "-": 24
   }
},
 {
   "Rank": 18,
   "SeasonGame": 17,
   "Date": "2003-12-03",
   "Age": "25-102",
   "Team": "LAL",
   "FIELD6": "@",
   "Opponent": "SAS",
   "FIELD8": "W (+4)",
   "GamesStarted": "1",
   "MinsPlayed": "46:02:00",
   "FieldGoals": 6,
   "FieldGoalsAttempted": 20,
   "FieldGoalPercentage": 0.3,
   "ThreePointFieldGoals": 1,
   "ThreePointFieldGoalAttempted": 4,
   "ThreePointFieldGoalPercentage": 0.25,
   "FreeThrows": 8,
   "FreeThrowAttempts": 9,
   "FreeThrowPercentage": 0.889,
   "OffensiveRebounds": 1,
   "DeffensiveRebounds": 5,
   "TotalRebounds": 6,
   "Assists": 3,
   "Steals": 2,
   "Blocks": 0,
   "Turnovers": 4,
   "PersonalFouls": 4,
   "Points": 21,
   "GameScore": 9.7,
   "+": {
      "-": 8
   }
},
 {
   "Rank": 19,
   "SeasonGame": 18,
   "Date": "2003-12-04",
   "Age": "25-103",
   "Team": "LAL",
   "FIELD6": "@",
   "Opponent": "DAL",
   "FIELD8": "W (+11)",
   "GamesStarted": "1",
   "MinsPlayed": "37:47:00",
   "FieldGoals": 9,
   "FieldGoalsAttempted": 23,
   "FieldGoalPercentage": 0.391,
   "ThreePointFieldGoals": 2,
   "ThreePointFieldGoalAttempted": 5,
   "ThreePointFieldGoalPercentage": 0.4,
   "FreeThrows": 12,
   "FreeThrowAttempts": 12,
   "FreeThrowPercentage": 1,
   "OffensiveRebounds": 4,
   "DeffensiveRebounds": 2,
   "TotalRebounds": 6,
   "Assists": 3,
   "Steals": 1,
   "Blocks": 0,
   "Turnovers": 3,
   "PersonalFouls": 3,
   "Points": 32,
   "GameScore": 21.8,
   "+": {
      "-": 10
   }
},
 {
   "Rank": 20,
   "SeasonGame": 19,
   "Date": "2003-12-07",
   "Age": "25-106",
   "Team": "LAL",
   "FIELD6": "",
   "Opponent": "UTA",
   "FIELD8": "W (+2)",
   "GamesStarted": "1",
   "MinsPlayed": "40:15:00",
   "FieldGoals": 4,
   "FieldGoalsAttempted": 17,
   "FieldGoalPercentage": 0.235,
   "ThreePointFieldGoals": 2,
   "ThreePointFieldGoalAttempted": 4,
   "ThreePointFieldGoalPercentage": 0.5,
   "FreeThrows": 9,
   "FreeThrowAttempts": 10,
   "FreeThrowPercentage": 0.9,
   "OffensiveRebounds": 2,
   "DeffensiveRebounds": 4,
   "TotalRebounds": 6,
   "Assists": 3,
   "Steals": 1,
   "Blocks": 0,
   "Turnovers": 2,
   "PersonalFouls": 4,
   "Points": 19,
   "GameScore": 10.4,
   "+": {
      "-": 3
   }
},
 {
   "Rank": 21,
   "SeasonGame": 20,
   "Date": "2003-12-09",
   "Age": "25-108",
   "Team": "LAL",
   "FIELD6": "",
   "Opponent": "NYK",
   "FIELD8": "W (+8)",
   "GamesStarted": "1",
   "MinsPlayed": "41:06:00",
   "FieldGoals": 7,
   "FieldGoalsAttempted": 16,
   "FieldGoalPercentage": 0.438,
   "ThreePointFieldGoals": 0,
   "ThreePointFieldGoalAttempted": 0,
   "ThreePointFieldGoalPercentage": null,
   "FreeThrows": 7,
   "FreeThrowAttempts": 8,
   "FreeThrowPercentage": 0.875,
   "OffensiveRebounds": 3,
   "DeffensiveRebounds": 3,
   "TotalRebounds": 6,
   "Assists": 9,
   "Steals": 1,
   "Blocks": 0,
   "Turnovers": 3,
   "PersonalFouls": 1,
   "Points": 21,
   "GameScore": 19.1,
   "+": {
      "-": 10
   }
},
 {
   "Rank": 22,
   "SeasonGame": 21,
   "Date": "2003-12-12",
   "Age": "25-111",
   "Team": "LAL",
   "FIELD6": "",
   "Opponent": "DAL",
   "FIELD8": "L (-17)",
   "GamesStarted": "1",
   "MinsPlayed": "40:55:00",
   "FieldGoals": 4,
   "FieldGoalsAttempted": 18,
   "FieldGoalPercentage": 0.222,
   "ThreePointFieldGoals": 0,
   "ThreePointFieldGoalAttempted": 3,
   "ThreePointFieldGoalPercentage": 0,
   "FreeThrows": 7,
   "FreeThrowAttempts": 7,
   "FreeThrowPercentage": 1,
   "OffensiveRebounds": 1,
   "DeffensiveRebounds": 6,
   "TotalRebounds": 7,
   "Assists": 6,
   "Steals": 1,
   "Blocks": 1,
   "Turnovers": 1,
   "PersonalFouls": 5,
   "Points": 15,
   "GameScore": 9.4,
   "+": {
      "-": -19
   }
},
 {
   "Rank": 23,
   "SeasonGame": 22,
   "Date": "2003-12-13",
   "Age": "25-112",
   "Team": "LAL",
   "FIELD6": "@",
   "Opponent": "POR",
   "FIELD8": "L (-4)",
   "GamesStarted": "1",
   "MinsPlayed": "41:56:00",
   "FieldGoals": 10,
   "FieldGoalsAttempted": 18,
   "FieldGoalPercentage": 0.556,
   "ThreePointFieldGoals": 1,
   "ThreePointFieldGoalAttempted": 3,
   "ThreePointFieldGoalPercentage": 0.333,
   "FreeThrows": 14,
   "FreeThrowAttempts": 15,
   "FreeThrowPercentage": 0.933,
   "OffensiveRebounds": 3,
   "DeffensiveRebounds": 2,
   "TotalRebounds": 5,
   "Assists": 6,
   "Steals": 0,
   "Blocks": 1,
   "Turnovers": 2,
   "PersonalFouls": 2,
   "Points": 35,
   "GameScore": 30.8,
   "+": {
      "-": 0
   }
},
 {
   "Rank": 24,
   "SeasonGame": 23,
   "Date": "2003-12-19",
   "Age": "25-118",
   "Team": "LAL",
   "FIELD6": "",
   "Opponent": "DEN",
   "FIELD8": "W (+2)",
   "GamesStarted": "0",
   "MinsPlayed": "30:50:00",
   "FieldGoals": 5,
   "FieldGoalsAttempted": 14,
   "FieldGoalPercentage": 0.357,
   "ThreePointFieldGoals": 0,
   "ThreePointFieldGoalAttempted": 2,
   "ThreePointFieldGoalPercentage": 0,
   "FreeThrows": 3,
   "FreeThrowAttempts": 4,
   "FreeThrowPercentage": 0.75,
   "OffensiveRebounds": 1,
   "DeffensiveRebounds": 2,
   "TotalRebounds": 3,
   "Assists": 5,
   "Steals": 0,
   "Blocks": 0,
   "Turnovers": 4,
   "PersonalFouls": 1,
   "Points": 13,
   "GameScore": 5.2,
   "+": {
      "-": -4
   }
},
 {
   "Rank": 25,
   "SeasonGame": 24,
   "Date": "2003-12-21",
   "Age": "25-120",
   "Team": "LAL",
   "FIELD6": "",
   "Opponent": "PHO",
   "FIELD8": "W (+6)",
   "GamesStarted": "1",
   "MinsPlayed": "39:38:00",
   "FieldGoals": 4,
   "FieldGoalsAttempted": 12,
   "FieldGoalPercentage": 0.333,
   "ThreePointFieldGoals": 0,
   "ThreePointFieldGoalAttempted": 2,
   "ThreePointFieldGoalPercentage": 0,
   "FreeThrows": 2,
   "FreeThrowAttempts": 3,
   "FreeThrowPercentage": 0.667,
   "OffensiveRebounds": 3,
   "DeffensiveRebounds": 3,
   "TotalRebounds": 6,
   "Assists": 4,
   "Steals": 0,
   "Blocks": 0,
   "Turnovers": 4,
   "PersonalFouls": 0,
   "Points": 10,
   "GameScore": 4.6,
   "+": {
      "-": 5
   }
},
 {
   "Rank": 26,
   "SeasonGame": 25,
   "Date": "2003-12-23",
   "Age": "25-122",
   "Team": "LAL",
   "FIELD6": "@",
   "Opponent": "GSW",
   "FIELD8": "L (-9)",
   "GamesStarted": "1",
   "MinsPlayed": "37:59:00",
   "FieldGoals": 8,
   "FieldGoalsAttempted": 16,
   "FieldGoalPercentage": 0.5,
   "ThreePointFieldGoals": 3,
   "ThreePointFieldGoalAttempted": 5,
   "ThreePointFieldGoalPercentage": 0.6,
   "FreeThrows": 4,
   "FreeThrowAttempts": 5,
   "FreeThrowPercentage": 0.8,
   "OffensiveRebounds": 1,
   "DeffensiveRebounds": 4,
   "TotalRebounds": 5,
   "Assists": 2,
   "Steals": 1,
   "Blocks": 1,
   "Turnovers": 4,
   "PersonalFouls": 5,
   "Points": 23,
   "GameScore": 13.6,
   "+": {
      "-": -7
   }
},
 {
   "Rank": 27,
   "SeasonGame": 26,
   "Date": "2003-12-25",
   "Age": "25-124",
   "Team": "LAL",
   "FIELD6": "",
   "Opponent": "HOU",
   "FIELD8": "L (-12)",
   "GamesStarted": "1",
   "MinsPlayed": "43:18:00",
   "FieldGoals": 9,
   "FieldGoalsAttempted": 26,
   "FieldGoalPercentage": 0.346,
   "ThreePointFieldGoals": 1,
   "ThreePointFieldGoalAttempted": 2,
   "ThreePointFieldGoalPercentage": 0.5,
   "FreeThrows": 4,
   "FreeThrowAttempts": 6,
   "FreeThrowPercentage": 0.667,
   "OffensiveRebounds": 3,
   "DeffensiveRebounds": 5,
   "TotalRebounds": 8,
   "Assists": 6,
   "Steals": 2,
   "Blocks": 0,
   "Turnovers": 3,
   "PersonalFouls": 4,
   "Points": 23,
   "GameScore": 12.8,
   "+": {
      "-": -7
   }
},
 {
   "Rank": 28,
   "SeasonGame": 27,
   "Date": "2003-12-28",
   "Age": "25-127",
   "Team": "LAL",
   "FIELD6": "",
   "Opponent": "BOS",
   "FIELD8": "W (+23)",
   "GamesStarted": "1",
   "MinsPlayed": "35:32:00",
   "FieldGoals": 5,
   "FieldGoalsAttempted": 18,
   "FieldGoalPercentage": 0.278,
   "ThreePointFieldGoals": 1,
   "ThreePointFieldGoalAttempted": 6,
   "ThreePointFieldGoalPercentage": 0.167,
   "FreeThrows": 0,
   "FreeThrowAttempts": 0,
   "FreeThrowPercentage": null,
   "OffensiveRebounds": 2,
   "DeffensiveRebounds": 3,
   "TotalRebounds": 5,
   "Assists": 6,
   "Steals": 2,
   "Blocks": 0,
   "Turnovers": 6,
   "PersonalFouls": 2,
   "Points": 11,
   "GameScore": 2.1,
   "+": {
      "-": 15
   }
},
 {
   "Rank": 29,
   "SeasonGame": 28,
   "Date": "2004-01-02",
   "Age": "25-132",
   "Team": "LAL",
   "FIELD6": "@",
   "Opponent": "SEA",
   "FIELD8": "L (-2)",
   "GamesStarted": "1",
   "MinsPlayed": "36:02:00",
   "FieldGoals": 11,
   "FieldGoalsAttempted": 25,
   "FieldGoalPercentage": 0.44,
   "ThreePointFieldGoals": 3,
   "ThreePointFieldGoalAttempted": 4,
   "ThreePointFieldGoalPercentage": 0.75,
   "FreeThrows": 7,
   "FreeThrowAttempts": 8,
   "FreeThrowPercentage": 0.875,
   "OffensiveRebounds": 2,
   "DeffensiveRebounds": 4,
   "TotalRebounds": 6,
   "Assists": 6,
   "Steals": 4,
   "Blocks": 0,
   "Turnovers": 3,
   "PersonalFouls": 4,
   "Points": 32,
   "GameScore": 24.7,
   "+": {
      "-": 4
   }
},
 {
   "Rank": 30,
   "SeasonGame": 29,
   "Date": "2004-01-04",
   "Age": "25-134",
   "Team": "LAL",
   "FIELD6": "@",
   "Opponent": "LAC",
   "FIELD8": "L (-3)",
   "GamesStarted": "1",
   "MinsPlayed": "39:34:00",
   "FieldGoals": 14,
   "FieldGoalsAttempted": 27,
   "FieldGoalPercentage": 0.519,
   "ThreePointFieldGoals": 4,
   "ThreePointFieldGoalAttempted": 7,
   "ThreePointFieldGoalPercentage": 0.571,
   "FreeThrows": 12,
   "FreeThrowAttempts": 15,
   "FreeThrowPercentage": 0.8,
   "OffensiveRebounds": 4,
   "DeffensiveRebounds": 6,
   "TotalRebounds": 10,
   "Assists": 3,
   "Steals": 4,
   "Blocks": 0,
   "Turnovers": 2,
   "PersonalFouls": 2,
   "Points": 44,
   "GameScore": 37.4,
   "+": {
      "-": -7
   }
},
 {
   "Rank": 31,
   "SeasonGame": 30,
   "Date": "2004-01-06",
   "Age": "25-136",
   "Team": "LAL",
   "FIELD6": "@",
   "Opponent": "MIN",
   "FIELD8": "L (-16)",
   "GamesStarted": "1",
   "MinsPlayed": "38:30:00",
   "FieldGoals": 8,
   "FieldGoalsAttempted": 17,
   "FieldGoalPercentage": 0.471,
   "ThreePointFieldGoals": 0,
   "ThreePointFieldGoalAttempted": 1,
   "ThreePointFieldGoalPercentage": 0,
   "FreeThrows": 4,
   "FreeThrowAttempts": 6,
   "FreeThrowPercentage": 0.667,
   "OffensiveRebounds": 2,
   "DeffensiveRebounds": 8,
   "TotalRebounds": 10,
   "Assists": 4,
   "Steals": 0,
   "Blocks": 0,
   "Turnovers": 1,
   "PersonalFouls": 4,
   "Points": 20,
   "GameScore": 14.5,
   "+": {
      "-": -17
   }
},
 {
   "Rank": 32,
   "SeasonGame": 31,
   "Date": "2004-01-07",
   "Age": "25-137",
   "Team": "LAL",
   "FIELD6": "@",
   "Opponent": "DEN",
   "FIELD8": "L (-22)",
   "GamesStarted": "1",
   "MinsPlayed": "37:11:00",
   "FieldGoals": 8,
   "FieldGoalsAttempted": 23,
   "FieldGoalPercentage": 0.348,
   "ThreePointFieldGoals": 1,
   "ThreePointFieldGoalAttempted": 4,
   "ThreePointFieldGoalPercentage": 0.25,
   "FreeThrows": 10,
   "FreeThrowAttempts": 11,
   "FreeThrowPercentage": 0.909,
   "OffensiveRebounds": 1,
   "DeffensiveRebounds": 2,
   "TotalRebounds": 3,
   "Assists": 6,
   "Steals": 6,
   "Blocks": 0,
   "Turnovers": 5,
   "PersonalFouls": 3,
   "Points": 27,
   "GameScore": 19,
   "+": {
      "-": -15
   }
},
 {
   "Rank": 33,
   "SeasonGame": 32,
   "Date": "2004-01-09",
   "Age": "25-139",
   "Team": "LAL",
   "FIELD6": "",
   "Opponent": "ATL",
   "FIELD8": "W (+46)",
   "GamesStarted": "1",
   "MinsPlayed": "30:50:00",
   "FieldGoals": 9,
   "FieldGoalsAttempted": 19,
   "FieldGoalPercentage": 0.474,
   "ThreePointFieldGoals": 2,
   "ThreePointFieldGoalAttempted": 5,
   "ThreePointFieldGoalPercentage": 0.4,
   "FreeThrows": 6,
   "FreeThrowAttempts": 6,
   "FreeThrowPercentage": 1,
   "OffensiveRebounds": 0,
   "DeffensiveRebounds": 5,
   "TotalRebounds": 5,
   "Assists": 6,
   "Steals": 3,
   "Blocks": 0,
   "Turnovers": 1,
   "PersonalFouls": 2,
   "Points": 26,
   "GameScore": 23.2,
   "+": {
      "-": 33
   }
},
 {
   "Rank": 34,
   "SeasonGame": 33,
   "Date": "2004-01-12",
   "Age": "25-142",
   "Team": "LAL",
   "FIELD6": "",
   "Opponent": "CLE",
   "FIELD8": "W (+10)",
   "GamesStarted": "1",
   "MinsPlayed": "17:05",
   "FieldGoals": 3,
   "FieldGoalsAttempted": 8,
   "FieldGoalPercentage": 0.375,
   "ThreePointFieldGoals": 0,
   "ThreePointFieldGoalAttempted": 0,
   "ThreePointFieldGoalPercentage": null,
   "FreeThrows": 4,
   "FreeThrowAttempts": 5,
   "FreeThrowPercentage": 0.8,
   "OffensiveRebounds": 1,
   "DeffensiveRebounds": 4,
   "TotalRebounds": 5,
   "Assists": 2,
   "Steals": 1,
   "Blocks": 0,
   "Turnovers": 0,
   "PersonalFouls": 1,
   "Points": 10,
   "GameScore": 9.1,
   "+": {
      "-": 2
   }
},
 {
   "Rank": 35,
   "SeasonGame": 34,
   "Date": "2004-01-24",
   "Age": "25-154",
   "Team": "LAL",
   "FIELD6": "@",
   "Opponent": "UTA",
   "FIELD8": "W (+7)",
   "GamesStarted": "1",
   "MinsPlayed": "37:31:00",
   "FieldGoals": 6,
   "FieldGoalsAttempted": 15,
   "FieldGoalPercentage": 0.4,
   "ThreePointFieldGoals": 1,
   "ThreePointFieldGoalAttempted": 4,
   "ThreePointFieldGoalPercentage": 0.25,
   "FreeThrows": 8,
   "FreeThrowAttempts": 13,
   "FreeThrowPercentage": 0.615,
   "OffensiveRebounds": 2,
   "DeffensiveRebounds": 2,
   "TotalRebounds": 4,
   "Assists": 6,
   "Steals": 0,
   "Blocks": 0,
   "Turnovers": 0,
   "PersonalFouls": 0,
   "Points": 21,
   "GameScore": 17.1,
   "+": {
      "-": 15
   }
},
 {
   "Rank": 36,
   "SeasonGame": 35,
   "Date": "2004-01-28",
   "Age": "25-158",
   "Team": "LAL",
   "FIELD6": "",
   "Opponent": "SEA",
   "FIELD8": "W (+14)",
   "GamesStarted": "1",
   "MinsPlayed": "29:01:00",
   "FieldGoals": 6,
   "FieldGoalsAttempted": 15,
   "FieldGoalPercentage": 0.4,
   "ThreePointFieldGoals": 0,
   "ThreePointFieldGoalAttempted": 3,
   "ThreePointFieldGoalPercentage": 0,
   "FreeThrows": 2,
   "FreeThrowAttempts": 3,
   "FreeThrowPercentage": 0.667,
   "OffensiveRebounds": 0,
   "DeffensiveRebounds": 2,
   "TotalRebounds": 2,
   "Assists": 3,
   "Steals": 0,
   "Blocks": 0,
   "Turnovers": 3,
   "PersonalFouls": 0,
   "Points": 14,
   "GameScore": 5.2,
   "+": {
      "-": 2
   }
},
 {
   "Rank": 37,
   "SeasonGame": 36,
   "Date": "2004-02-11",
   "Age": "25-172",
   "Team": "LAL",
   "FIELD6": "@",
   "Opponent": "HOU",
   "FIELD8": "L (-15)",
   "GamesStarted": "1",
   "MinsPlayed": "35:36:00",
   "FieldGoals": 4,
   "FieldGoalsAttempted": 7,
   "FieldGoalPercentage": 0.571,
   "ThreePointFieldGoals": 4,
   "ThreePointFieldGoalAttempted": 5,
   "ThreePointFieldGoalPercentage": 0.8,
   "FreeThrows": 2,
   "FreeThrowAttempts": 2,
   "FreeThrowPercentage": 1,
   "OffensiveRebounds": 0,
   "DeffensiveRebounds": 1,
   "TotalRebounds": 1,
   "Assists": 3,
   "Steals": 0,
   "Blocks": 0,
   "Turnovers": 1,
   "PersonalFouls": 3,
   "Points": 14,
   "GameScore": 10.9,
   "+": {
      "-": -7
   }
},
 {
   "Rank": 38,
   "SeasonGame": 37,
   "Date": "2004-02-17",
   "Age": "25-178",
   "Team": "LAL",
   "FIELD6": "",
   "Opponent": "POR",
   "FIELD8": "W (+3)",
   "GamesStarted": "1",
   "MinsPlayed": "41:20:00",
   "FieldGoals": 13,
   "FieldGoalsAttempted": 23,
   "FieldGoalPercentage": 0.565,
   "ThreePointFieldGoals": 0,
   "ThreePointFieldGoalAttempted": 1,
   "ThreePointFieldGoalPercentage": 0,
   "FreeThrows": 5,
   "FreeThrowAttempts": 9,
   "FreeThrowPercentage": 0.556,
   "OffensiveRebounds": 4,
   "DeffensiveRebounds": 4,
   "TotalRebounds": 8,
   "Assists": 10,
   "Steals": 2,
   "Blocks": 0,
   "Turnovers": 4,
   "PersonalFouls": 1,
   "Points": 31,
   "GameScore": 27.1,
   "+": {
      "-": 11
   }
},
 {
   "Rank": 39,
   "SeasonGame": 38,
   "Date": "2004-02-18",
   "Age": "25-179",
   "Team": "LAL",
   "FIELD6": "@",
   "Opponent": "GSW",
   "FIELD8": "W (+1)",
   "GamesStarted": "1",
   "MinsPlayed": "43:39:00",
   "FieldGoals": 11,
   "FieldGoalsAttempted": 16,
   "FieldGoalPercentage": 0.688,
   "ThreePointFieldGoals": 0,
   "ThreePointFieldGoalAttempted": 1,
   "ThreePointFieldGoalPercentage": 0,
   "FreeThrows": 13,
   "FreeThrowAttempts": 15,
   "FreeThrowPercentage": 0.867,
   "OffensiveRebounds": 2,
   "DeffensiveRebounds": 4,
   "TotalRebounds": 6,
   "Assists": 8,
   "Steals": 2,
   "Blocks": 1,
   "Turnovers": 5,
   "PersonalFouls": 1,
   "Points": 35,
   "GameScore": 32.9,
   "+": {
      "-": -1
   }
},
 {
   "Rank": 40,
   "SeasonGame": 39,
   "Date": "2004-02-20",
   "Age": "25-181",
   "Team": "LAL",
   "FIELD6": "",
   "Opponent": "PHI",
   "FIELD8": "W (+28)",
   "GamesStarted": "1",
   "MinsPlayed": "29:15:00",
   "FieldGoals": 10,
   "FieldGoalsAttempted": 18,
   "FieldGoalPercentage": 0.556,
   "ThreePointFieldGoals": 1,
   "ThreePointFieldGoalAttempted": 2,
   "ThreePointFieldGoalPercentage": 0.5,
   "FreeThrows": 7,
   "FreeThrowAttempts": 8,
   "FreeThrowPercentage": 0.875,
   "OffensiveRebounds": 4,
   "DeffensiveRebounds": 1,
   "TotalRebounds": 5,
   "Assists": 7,
   "Steals": 3,
   "Blocks": 2,
   "Turnovers": 2,
   "PersonalFouls": 4,
   "Points": 28,
   "GameScore": 27.8,
   "+": {
      "-": 15
   }
},
 {
   "Rank": 41,
   "SeasonGame": 40,
   "Date": "2004-02-22",
   "Age": "25-183",
   "Team": "LAL",
   "FIELD6": "@",
   "Opponent": "PHO",
   "FIELD8": "W (+12)",
   "GamesStarted": "1",
   "MinsPlayed": "42:04:00",
   "FieldGoals": 15,
   "FieldGoalsAttempted": 25,
   "FieldGoalPercentage": 0.6,
   "ThreePointFieldGoals": 2,
   "ThreePointFieldGoalAttempted": 5,
   "ThreePointFieldGoalPercentage": 0.4,
   "FreeThrows": 8,
   "FreeThrowAttempts": 8,
   "FreeThrowPercentage": 1,
   "OffensiveRebounds": 4,
   "DeffensiveRebounds": 3,
   "TotalRebounds": 7,
   "Assists": 5,
   "Steals": 3,
   "Blocks": 0,
   "Turnovers": 2,
   "PersonalFouls": 0,
   "Points": 40,
   "GameScore": 36.7,
   "+": {
      "-": 9
   }
},
 {
   "Rank": 42,
   "SeasonGame": 41,
   "Date": "2004-02-25",
   "Age": "25-186",
   "Team": "LAL",
   "FIELD6": "@",
   "Opponent": "DEN",
   "FIELD8": "W (+1)",
   "GamesStarted": "1",
   "MinsPlayed": "41:09:00",
   "FieldGoals": 14,
   "FieldGoalsAttempted": 26,
   "FieldGoalPercentage": 0.538,
   "ThreePointFieldGoals": 2,
   "ThreePointFieldGoalAttempted": 4,
   "ThreePointFieldGoalPercentage": 0.5,
   "FreeThrows": 5,
   "FreeThrowAttempts": 5,
   "FreeThrowPercentage": 1,
   "OffensiveRebounds": 2,
   "DeffensiveRebounds": 5,
   "TotalRebounds": 7,
   "Assists": 10,
   "Steals": 3,
   "Blocks": 0,
   "Turnovers": 3,
   "PersonalFouls": 2,
   "Points": 35,
   "GameScore": 31.5,
   "+": {
      "-": 5
   }
},
 {
   "Rank": 43,
   "SeasonGame": 42,
   "Date": "2004-02-26",
   "Age": "25-187",
   "Team": "LAL",
   "FIELD6": "",
   "Opponent": "SAC",
   "FIELD8": "L (-2)",
   "GamesStarted": "1",
   "MinsPlayed": "41:32:00",
   "FieldGoals": 12,
   "FieldGoalsAttempted": 28,
   "FieldGoalPercentage": 0.429,
   "ThreePointFieldGoals": 2,
   "ThreePointFieldGoalAttempted": 6,
   "ThreePointFieldGoalPercentage": 0.333,
   "FreeThrows": 9,
   "FreeThrowAttempts": 10,
   "FreeThrowPercentage": 0.9,
   "OffensiveRebounds": 3,
   "DeffensiveRebounds": 8,
   "TotalRebounds": 11,
   "Assists": 6,
   "Steals": 1,
   "Blocks": 0,
   "Turnovers": 4,
   "PersonalFouls": 2,
   "Points": 35,
   "GameScore": 24.7,
   "+": {
      "-": -6
   }
},
 {
   "Rank": 44,
   "SeasonGame": 43,
   "Date": "2004-02-28",
   "Age": "25-189",
   "Team": "LAL",
   "FIELD6": "@",
   "Opponent": "WAS",
   "FIELD8": "W (+12)",
   "GamesStarted": "1",
   "MinsPlayed": "38:27:00",
   "FieldGoals": 8,
   "FieldGoalsAttempted": 16,
   "FieldGoalPercentage": 0.5,
   "ThreePointFieldGoals": 2,
   "ThreePointFieldGoalAttempted": 4,
   "ThreePointFieldGoalPercentage": 0.5,
   "FreeThrows": 7,
   "FreeThrowAttempts": 8,
   "FreeThrowPercentage": 0.875,
   "OffensiveRebounds": 3,
   "DeffensiveRebounds": 11,
   "TotalRebounds": 14,
   "Assists": 10,
   "Steals": 2,
   "Blocks": 0,
   "Turnovers": 2,
   "PersonalFouls": 3,
   "Points": 25,
   "GameScore": 27.8,
   "+": {
      "-": 11
   }
},
 {
   "Rank": 45,
   "SeasonGame": 44,
   "Date": "2004-02-29",
   "Age": "25-190",
   "Team": "LAL",
   "FIELD6": "@",
   "Opponent": "NJN",
   "FIELD8": "W (+17)",
   "GamesStarted": "1",
   "MinsPlayed": "32:40:00",
   "FieldGoals": 4,
   "FieldGoalsAttempted": 12,
   "FieldGoalPercentage": 0.333,
   "ThreePointFieldGoals": 2,
   "ThreePointFieldGoalAttempted": 6,
   "ThreePointFieldGoalPercentage": 0.333,
   "FreeThrows": 1,
   "FreeThrowAttempts": 2,
   "FreeThrowPercentage": 0.5,
   "OffensiveRebounds": 1,
   "DeffensiveRebounds": 5,
   "TotalRebounds": 6,
   "Assists": 10,
   "Steals": 1,
   "Blocks": 0,
   "Turnovers": 4,
   "PersonalFouls": 3,
   "Points": 11,
   "GameScore": 8.8,
   "+": {
      "-": 19
   }
},
 {
   "Rank": 46,
   "SeasonGame": null,
   "Date": "2004-03-02",
   "Age": "25-192",
   "Team": "LAL",
   "FIELD6": "@",
   "Opponent": "ATL",
   "FIELD8": "L (-1)",
   "GamesStarted": "Not With Team",
   "MinsPlayed": "",
   "FieldGoals": null,
   "FieldGoalsAttempted": null,
   "FieldGoalPercentage": null,
   "ThreePointFieldGoals": null,
   "ThreePointFieldGoalAttempted": null,
   "ThreePointFieldGoalPercentage": null,
   "FreeThrows": null,
   "FreeThrowAttempts": null,
   "FreeThrowPercentage": null,
   "OffensiveRebounds": null,
   "DeffensiveRebounds": null,
   "TotalRebounds": null,
   "Assists": null,
   "Steals": null,
   "Blocks": null,
   "Turnovers": null,
   "PersonalFouls": null,
   "Points": null,
   "GameScore": null,
   "+": {
      "-": null
   }
},
 {
   "Rank": 47,
   "SeasonGame": 45,
   "Date": "2004-03-03",
   "Age": "25-193",
   "Team": "LAL",
   "FIELD6": "@",
   "Opponent": "HOU",
   "FIELD8": "W (+3)",
   "GamesStarted": "1",
   "MinsPlayed": "46:17:00",
   "FieldGoals": 7,
   "FieldGoalsAttempted": 19,
   "FieldGoalPercentage": 0.368,
   "ThreePointFieldGoals": 0,
   "ThreePointFieldGoalAttempted": 5,
   "ThreePointFieldGoalPercentage": 0,
   "FreeThrows": 4,
   "FreeThrowAttempts": 4,
   "FreeThrowPercentage": 1,
   "OffensiveRebounds": 0,
   "DeffensiveRebounds": 8,
   "TotalRebounds": 8,
   "Assists": 13,
   "Steals": 0,
   "Blocks": 0,
   "Turnovers": 4,
   "PersonalFouls": 2,
   "Points": 18,
   "GameScore": 14.2,
   "+": {
      "-": 9
   }
},
 {
   "Rank": 48,
   "SeasonGame": 46,
   "Date": "2004-03-05",
   "Age": "25-195",
   "Team": "LAL",
   "FIELD6": "",
   "Opponent": "SEA",
   "FIELD8": "W (+8)",
   "GamesStarted": "1",
   "MinsPlayed": "0:54",
   "FieldGoals": 0,
   "FieldGoalsAttempted": 0,
   "FieldGoalPercentage": null,
   "ThreePointFieldGoals": 0,
   "ThreePointFieldGoalAttempted": 0,
   "ThreePointFieldGoalPercentage": null,
   "FreeThrows": 0,
   "FreeThrowAttempts": 0,
   "FreeThrowPercentage": null,
   "OffensiveRebounds": 0,
   "DeffensiveRebounds": 0,
   "TotalRebounds": 0,
   "Assists": 0,
   "Steals": 0,
   "Blocks": 0,
   "Turnovers": 0,
   "PersonalFouls": 1,
   "Points": 0,
   "GameScore": -0.4,
   "+": {
      "-": 3
   }
},
 {
   "Rank": 49,
   "SeasonGame": null,
   "Date": "2004-03-07",
   "Age": "25-197",
   "Team": "LAL",
   "FIELD6": "",
   "Opponent": "NJN",
   "FIELD8": "W (+6)",
   "GamesStarted": "Did Not Dress",
   "MinsPlayed": "",
   "FieldGoals": null,
   "FieldGoalsAttempted": null,
   "FieldGoalPercentage": null,
   "ThreePointFieldGoals": null,
   "ThreePointFieldGoalAttempted": null,
   "ThreePointFieldGoalPercentage": null,
   "FreeThrows": null,
   "FreeThrowAttempts": null,
   "FreeThrowPercentage": null,
   "OffensiveRebounds": null,
   "DeffensiveRebounds": null,
   "TotalRebounds": null,
   "Assists": null,
   "Steals": null,
   "Blocks": null,
   "Turnovers": null,
   "PersonalFouls": null,
   "Points": null,
   "GameScore": null,
   "+": {
      "-": null
   }
},
 {
   "Rank": 50,
   "SeasonGame": null,
   "Date": "2004-03-08",
   "Age": "25-198",
   "Team": "LAL",
   "FIELD6": "@",
   "Opponent": "UTA",
   "FIELD8": "L (-5)",
   "GamesStarted": "Did Not Play",
   "MinsPlayed": "",
   "FieldGoals": null,
   "FieldGoalsAttempted": null,
   "FieldGoalPercentage": null,
   "ThreePointFieldGoals": null,
   "ThreePointFieldGoalAttempted": null,
   "ThreePointFieldGoalPercentage": null,
   "FreeThrows": null,
   "FreeThrowAttempts": null,
   "FreeThrowPercentage": null,
   "OffensiveRebounds": null,
   "DeffensiveRebounds": null,
   "TotalRebounds": null,
   "Assists": null,
   "Steals": null,
   "Blocks": null,
   "Turnovers": null,
   "PersonalFouls": null,
   "Points": null,
   "GameScore": null,
   "+": {
      "-": null
   }
},
 {
   "Rank": 51,
   "SeasonGame": 47,
   "Date": "2004-03-10",
   "Age": "25-200",
   "Team": "LAL",
   "FIELD6": "@",
   "Opponent": "BOS",
   "FIELD8": "W (+8)",
   "GamesStarted": "1",
   "MinsPlayed": "40:32:00",
   "FieldGoals": 4,
   "FieldGoalsAttempted": 16,
   "FieldGoalPercentage": 0.25,
   "ThreePointFieldGoals": 0,
   "ThreePointFieldGoalAttempted": 2,
   "ThreePointFieldGoalPercentage": 0,
   "FreeThrows": 10,
   "FreeThrowAttempts": 14,
   "FreeThrowPercentage": 0.714,
   "OffensiveRebounds": 3,
   "DeffensiveRebounds": 2,
   "TotalRebounds": 5,
   "Assists": 10,
   "Steals": 3,
   "Blocks": 0,
   "Turnovers": 3,
   "PersonalFouls": 2,
   "Points": 18,
   "GameScore": 15.7,
   "+": {
      "-": 13
   }
},
 {
   "Rank": 52,
   "SeasonGame": 48,
   "Date": "2004-03-12",
   "Age": "25-202",
   "Team": "LAL",
   "FIELD6": "@",
   "Opponent": "MIN",
   "FIELD8": "L (-10)",
   "GamesStarted": "1",
   "MinsPlayed": "37:49:00",
   "FieldGoals": 6,
   "FieldGoalsAttempted": 20,
   "FieldGoalPercentage": 0.3,
   "ThreePointFieldGoals": 1,
   "ThreePointFieldGoalAttempted": 3,
   "ThreePointFieldGoalPercentage": 0.333,
   "FreeThrows": 3,
   "FreeThrowAttempts": 3,
   "FreeThrowPercentage": 1,
   "OffensiveRebounds": 2,
   "DeffensiveRebounds": 9,
   "TotalRebounds": 11,
   "Assists": 5,
   "Steals": 0,
   "Blocks": 0,
   "Turnovers": 2,
   "PersonalFouls": 2,
   "Points": 16,
   "GameScore": 9.2,
   "+": {
      "-": -1
   }
},
 {
   "Rank": 53,
   "SeasonGame": 49,
   "Date": "2004-03-13",
   "Age": "25-203",
   "Team": "LAL",
   "FIELD6": "@",
   "Opponent": "CHI",
   "FIELD8": "W (+7)",
   "GamesStarted": "1",
   "MinsPlayed": "38:04:00",
   "FieldGoals": 12,
   "FieldGoalsAttempted": 25,
   "FieldGoalPercentage": 0.48,
   "ThreePointFieldGoals": 1,
   "ThreePointFieldGoalAttempted": 4,
   "ThreePointFieldGoalPercentage": 0.25,
   "FreeThrows": 10,
   "FreeThrowAttempts": 11,
   "FreeThrowPercentage": 0.909,
   "OffensiveRebounds": 2,
   "DeffensiveRebounds": 6,
   "TotalRebounds": 8,
   "Assists": 3,
   "Steals": 2,
   "Blocks": 1,
   "Turnovers": 5,
   "PersonalFouls": 2,
   "Points": 35,
   "GameScore": 24.1,
   "+": {
      "-": 4
   }
},
 {
   "Rank": 54,
   "SeasonGame": 50,
   "Date": "2004-03-15",
   "Age": "25-205",
   "Team": "LAL",
   "FIELD6": "",
   "Opponent": "ORL",
   "FIELD8": "W (+3)",
   "GamesStarted": "1",
   "MinsPlayed": "44:34:00",
   "FieldGoals": 13,
   "FieldGoalsAttempted": 26,
   "FieldGoalPercentage": 0.5,
   "ThreePointFieldGoals": 2,
   "ThreePointFieldGoalAttempted": 5,
   "ThreePointFieldGoalPercentage": 0.4,
   "FreeThrows": 10,
   "FreeThrowAttempts": 13,
   "FreeThrowPercentage": 0.769,
   "OffensiveRebounds": 1,
   "DeffensiveRebounds": 2,
   "TotalRebounds": 3,
   "Assists": 4,
   "Steals": 1,
   "Blocks": 1,
   "Turnovers": 1,
   "PersonalFouls": 5,
   "Points": 38,
   "GameScore": 26.6,
   "+": {
      "-": 3
   }
},
 {
   "Rank": 55,
   "SeasonGame": 51,
   "Date": "2004-03-17",
   "Age": "25-207",
   "Team": "LAL",
   "FIELD6": "@",
   "Opponent": "LAC",
   "FIELD8": "W (+3)",
   "GamesStarted": "1",
   "MinsPlayed": "39:04:00",
   "FieldGoals": 11,
   "FieldGoalsAttempted": 17,
   "FieldGoalPercentage": 0.647,
   "ThreePointFieldGoals": 1,
   "ThreePointFieldGoalAttempted": 3,
   "ThreePointFieldGoalPercentage": 0.333,
   "FreeThrows": 4,
   "FreeThrowAttempts": 4,
   "FreeThrowPercentage": 1,
   "OffensiveRebounds": 1,
   "DeffensiveRebounds": 8,
   "TotalRebounds": 9,
   "Assists": 6,
   "Steals": 1,
   "Blocks": 1,
   "Turnovers": 3,
   "PersonalFouls": 2,
   "Points": 27,
   "GameScore": 24.7,
   "+": {
      "-": 4
   }
},
 {
   "Rank": 56,
   "SeasonGame": 52,
   "Date": "2004-03-19",
   "Age": "25-209",
   "Team": "LAL",
   "FIELD6": "",
   "Opponent": "LAC",
   "FIELD8": "W (+6)",
   "GamesStarted": "1",
   "MinsPlayed": "39:15:00",
   "FieldGoals": 10,
   "FieldGoalsAttempted": 20,
   "FieldGoalPercentage": 0.5,
   "ThreePointFieldGoals": 0,
   "ThreePointFieldGoalAttempted": 2,
   "ThreePointFieldGoalPercentage": 0,
   "FreeThrows": 7,
   "FreeThrowAttempts": 8,
   "FreeThrowPercentage": 0.875,
   "OffensiveRebounds": 2,
   "DeffensiveRebounds": 5,
   "TotalRebounds": 7,
   "Assists": 3,
   "Steals": 5,
   "Blocks": 0,
   "Turnovers": 3,
   "PersonalFouls": 4,
   "Points": 27,
   "GameScore": 22,
   "+": {
      "-": 1
   }
},
 {
   "Rank": 57,
   "SeasonGame": 53,
   "Date": "2004-03-21",
   "Age": "25-211",
   "Team": "LAL",
   "FIELD6": "",
   "Opponent": "MIL",
   "FIELD8": "W (+1)",
   "GamesStarted": "1",
   "MinsPlayed": "38:27:00",
   "FieldGoals": 7,
   "FieldGoalsAttempted": 17,
   "FieldGoalPercentage": 0.412,
   "ThreePointFieldGoals": 0,
   "ThreePointFieldGoalAttempted": 1,
   "ThreePointFieldGoalPercentage": 0,
   "FreeThrows": 8,
   "FreeThrowAttempts": 8,
   "FreeThrowPercentage": 1,
   "OffensiveRebounds": 3,
   "DeffensiveRebounds": 2,
   "TotalRebounds": 5,
   "Assists": 4,
   "Steals": 1,
   "Blocks": 1,
   "Turnovers": 5,
   "PersonalFouls": 2,
   "Points": 22,
   "GameScore": 14.3,
   "+": {
      "-": 4
   }
},
 {
   "Rank": 58,
   "SeasonGame": 54,
   "Date": "2004-03-24",
   "Age": "25-214",
   "Team": "LAL",
   "FIELD6": "",
   "Opponent": "SAC",
   "FIELD8": "W (+24)",
   "GamesStarted": "1",
   "MinsPlayed": "36:19:00",
   "FieldGoals": 11,
   "FieldGoalsAttempted": 23,
   "FieldGoalPercentage": 0.478,
   "ThreePointFieldGoals": 2,
   "ThreePointFieldGoalAttempted": 5,
   "ThreePointFieldGoalPercentage": 0.4,
   "FreeThrows": 12,
   "FreeThrowAttempts": 12,
   "FreeThrowPercentage": 1,
   "OffensiveRebounds": 2,
   "DeffensiveRebounds": 4,
   "TotalRebounds": 6,
   "Assists": 6,
   "Steals": 1,
   "Blocks": 0,
   "Turnovers": 0,
   "PersonalFouls": 3,
   "Points": 36,
   "GameScore": 30.9,
   "+": {
      "-": 25
   }
},
 {
   "Rank": 59,
   "SeasonGame": 55,
   "Date": "2004-03-26",
   "Age": "25-216",
   "Team": "LAL",
   "FIELD6": "",
   "Opponent": "MIN",
   "FIELD8": "W (+17)",
   "GamesStarted": "1",
   "MinsPlayed": "36:41:00",
   "FieldGoals": 13,
   "FieldGoalsAttempted": 21,
   "FieldGoalPercentage": 0.619,
   "ThreePointFieldGoals": 2,
   "ThreePointFieldGoalAttempted": 4,
   "ThreePointFieldGoalPercentage": 0.5,
   "FreeThrows": 7,
   "FreeThrowAttempts": 7,
   "FreeThrowPercentage": 1,
   "OffensiveRebounds": 2,
   "DeffensiveRebounds": 7,
   "TotalRebounds": 9,
   "Assists": 5,
   "Steals": 2,
   "Blocks": 2,
   "Turnovers": 4,
   "PersonalFouls": 2,
   "Points": 35,
   "GameScore": 31.1,
   "+": {
      "-": 17
   }
},
 {
   "Rank": 60,
   "SeasonGame": 56,
   "Date": "2004-03-28",
   "Age": "25-218",
   "Team": "LAL",
   "FIELD6": "",
   "Opponent": "UTA",
   "FIELD8": "W (+7)",
   "GamesStarted": "1",
   "MinsPlayed": "40:19:00",
   "FieldGoals": 8,
   "FieldGoalsAttempted": 23,
   "FieldGoalPercentage": 0.348,
   "ThreePointFieldGoals": 1,
   "ThreePointFieldGoalAttempted": 3,
   "ThreePointFieldGoalPercentage": 0.333,
   "FreeThrows": 17,
   "FreeThrowAttempts": 21,
   "FreeThrowPercentage": 0.81,
   "OffensiveRebounds": 1,
   "DeffensiveRebounds": 5,
   "TotalRebounds": 6,
   "Assists": 4,
   "Steals": 1,
   "Blocks": 1,
   "Turnovers": 1,
   "PersonalFouls": 5,
   "Points": 34,
   "GameScore": 23.2,
   "+": {
      "-": 12
   }
},
 {
   "Rank": 61,
   "SeasonGame": 57,
   "Date": "2004-03-30",
   "Age": "25-220",
   "Team": "LAL",
   "FIELD6": "",
   "Opponent": "NOH",
   "FIELD8": "W (+19)",
   "GamesStarted": "1",
   "MinsPlayed": "34:21:00",
   "FieldGoals": 7,
   "FieldGoalsAttempted": 17,
   "FieldGoalPercentage": 0.412,
   "ThreePointFieldGoals": 3,
   "ThreePointFieldGoalAttempted": 7,
   "ThreePointFieldGoalPercentage": 0.429,
   "FreeThrows": 6,
   "FreeThrowAttempts": 6,
   "FreeThrowPercentage": 1,
   "OffensiveRebounds": 1,
   "DeffensiveRebounds": 2,
   "TotalRebounds": 3,
   "Assists": 6,
   "Steals": 1,
   "Blocks": 0,
   "Turnovers": 4,
   "PersonalFouls": 3,
   "Points": 23,
   "GameScore": 15.2,
   "+": {
      "-": 12
   }
},
 {
   "Rank": 62,
   "SeasonGame": 58,
   "Date": "2004-04-01",
   "Age": "25-222",
   "Team": "LAL",
   "FIELD6": "",
   "Opponent": "HOU",
   "FIELD8": "W (+8)",
   "GamesStarted": "1",
   "MinsPlayed": "45:14:00",
   "FieldGoals": 8,
   "FieldGoalsAttempted": 19,
   "FieldGoalPercentage": 0.421,
   "ThreePointFieldGoals": 1,
   "ThreePointFieldGoalAttempted": 2,
   "ThreePointFieldGoalPercentage": 0.5,
   "FreeThrows": 9,
   "FreeThrowAttempts": 12,
   "FreeThrowPercentage": 0.75,
   "OffensiveRebounds": 2,
   "DeffensiveRebounds": 5,
   "TotalRebounds": 7,
   "Assists": 4,
   "Steals": 5,
   "Blocks": 1,
   "Turnovers": 6,
   "PersonalFouls": 2,
   "Points": 26,
   "GameScore": 19.3,
   "+": {
      "-": 6
   }
},
 {
   "Rank": 63,
   "SeasonGame": 59,
   "Date": "2004-04-02",
   "Age": "25-223",
   "Team": "LAL",
   "FIELD6": "@",
   "Opponent": "SEA",
   "FIELD8": "W (+11)",
   "GamesStarted": "1",
   "MinsPlayed": "39:27:00",
   "FieldGoals": 9,
   "FieldGoalsAttempted": 18,
   "FieldGoalPercentage": 0.5,
   "ThreePointFieldGoals": 3,
   "ThreePointFieldGoalAttempted": 5,
   "ThreePointFieldGoalPercentage": 0.6,
   "FreeThrows": 4,
   "FreeThrowAttempts": 6,
   "FreeThrowPercentage": 0.667,
   "OffensiveRebounds": 0,
   "DeffensiveRebounds": 1,
   "TotalRebounds": 1,
   "Assists": 2,
   "Steals": 2,
   "Blocks": 0,
   "Turnovers": 3,
   "PersonalFouls": 4,
   "Points": 25,
   "GameScore": 14.3,
   "+": {
      "-": -5
   }
},
 {
   "Rank": 64,
   "SeasonGame": 60,
   "Date": "2004-04-04",
   "Age": "25-225",
   "Team": "LAL",
   "FIELD6": "",
   "Opponent": "SAS",
   "FIELD8": "L (-6)",
   "GamesStarted": "1",
   "MinsPlayed": "44:09:00",
   "FieldGoals": 9,
   "FieldGoalsAttempted": 26,
   "FieldGoalPercentage": 0.346,
   "ThreePointFieldGoals": 2,
   "ThreePointFieldGoalAttempted": 7,
   "ThreePointFieldGoalPercentage": 0.286,
   "FreeThrows": 8,
   "FreeThrowAttempts": 10,
   "FreeThrowPercentage": 0.8,
   "OffensiveRebounds": 1,
   "DeffensiveRebounds": 5,
   "TotalRebounds": 6,
   "Assists": 3,
   "Steals": 0,
   "Blocks": 2,
   "Turnovers": 3,
   "PersonalFouls": 2,
   "Points": 28,
   "GameScore": 14.5,
   "+": {
      "-": 0
   }
},
 {
   "Rank": 65,
   "SeasonGame": 61,
   "Date": "2004-04-06",
   "Age": "25-227",
   "Team": "LAL",
   "FIELD6": "",
   "Opponent": "POR",
   "FIELD8": "L (-11)",
   "GamesStarted": "1",
   "MinsPlayed": "42:54:00",
   "FieldGoals": 5,
   "FieldGoalsAttempted": 23,
   "FieldGoalPercentage": 0.217,
   "ThreePointFieldGoals": 0,
   "ThreePointFieldGoalAttempted": 6,
   "ThreePointFieldGoalPercentage": 0,
   "FreeThrows": 2,
   "FreeThrowAttempts": 2,
   "FreeThrowPercentage": 1,
   "OffensiveRebounds": 2,
   "DeffensiveRebounds": 4,
   "TotalRebounds": 6,
   "Assists": 8,
   "Steals": 1,
   "Blocks": 1,
   "Turnovers": 3,
   "PersonalFouls": 2,
   "Points": 12,
   "GameScore": 4,
   "+": {
      "-": -14
   }
},
 {
   "Rank": 66,
   "SeasonGame": 62,
   "Date": "2004-04-09",
   "Age": "25-230",
   "Team": "LAL",
   "FIELD6": "",
   "Opponent": "MEM",
   "FIELD8": "W (+8)",
   "GamesStarted": "1",
   "MinsPlayed": "45:00:00",
   "FieldGoals": 9,
   "FieldGoalsAttempted": 23,
   "FieldGoalPercentage": 0.391,
   "ThreePointFieldGoals": 1,
   "ThreePointFieldGoalAttempted": 4,
   "ThreePointFieldGoalPercentage": 0.25,
   "FreeThrows": 14,
   "FreeThrowAttempts": 15,
   "FreeThrowPercentage": 0.933,
   "OffensiveRebounds": 1,
   "DeffensiveRebounds": 5,
   "TotalRebounds": 6,
   "Assists": 7,
   "Steals": 4,
   "Blocks": 1,
   "Turnovers": 3,
   "PersonalFouls": 2,
   "Points": 33,
   "GameScore": 28.1,
   "+": {
      "-": 12
   }
},
 {
   "Rank": 67,
   "SeasonGame": 63,
   "Date": "2004-04-11",
   "Age": "25-232",
   "Team": "LAL",
   "FIELD6": "@",
   "Opponent": "SAC",
   "FIELD8": "L (-17)",
   "GamesStarted": "1",
   "MinsPlayed": "41:24:00",
   "FieldGoals": 3,
   "FieldGoalsAttempted": 13,
   "FieldGoalPercentage": 0.231,
   "ThreePointFieldGoals": 0,
   "ThreePointFieldGoalAttempted": 3,
   "ThreePointFieldGoalPercentage": 0,
   "FreeThrows": 2,
   "FreeThrowAttempts": 3,
   "FreeThrowPercentage": 0.667,
   "OffensiveRebounds": 1,
   "DeffensiveRebounds": 4,
   "TotalRebounds": 5,
   "Assists": 4,
   "Steals": 2,
   "Blocks": 0,
   "Turnovers": 3,
   "PersonalFouls": 4,
   "Points": 8,
   "GameScore": 1.8,
   "+": {
      "-": -26
   }
},
 {
   "Rank": 68,
   "SeasonGame": 64,
   "Date": "2004-04-13",
   "Age": "25-234",
   "Team": "LAL",
   "FIELD6": "",
   "Opponent": "GSW",
   "FIELD8": "W (+5)",
   "GamesStarted": "1",
   "MinsPlayed": "43:10:00",
   "FieldGoals": 14,
   "FieldGoalsAttempted": 29,
   "FieldGoalPercentage": 0.483,
   "ThreePointFieldGoals": 0,
   "ThreePointFieldGoalAttempted": 6,
   "ThreePointFieldGoalPercentage": 0,
   "FreeThrows": 17,
   "FreeThrowAttempts": 18,
   "FreeThrowPercentage": 0.944,
   "OffensiveRebounds": 0,
   "DeffensiveRebounds": 7,
   "TotalRebounds": 7,
   "Assists": 8,
   "Steals": 2,
   "Blocks": 2,
   "Turnovers": 1,
   "PersonalFouls": 2,
   "Points": 45,
   "GameScore": 39.2,
   "+": {
      "-": 9
   }
},
 {
   "Rank": 69,
   "SeasonGame": 65,
   "Date": "2004-04-14",
   "Age": "25-235",
   "Team": "LAL",
   "FIELD6": "@",
   "Opponent": "POR",
   "FIELD8": "W (+1)",
   "GamesStarted": "1",
   "MinsPlayed": "53:28:00",
   "FieldGoals": 14,
   "FieldGoalsAttempted": 31,
   "FieldGoalPercentage": 0.452,
   "ThreePointFieldGoals": 4,
   "ThreePointFieldGoalAttempted": 10,
   "ThreePointFieldGoalPercentage": 0.4,
   "FreeThrows": 5,
   "FreeThrowAttempts": 9,
   "FreeThrowPercentage": 0.556,
   "OffensiveRebounds": 0,
   "DeffensiveRebounds": 8,
   "TotalRebounds": 8,
   "Assists": 5,
   "Steals": 1,
   "Blocks": 1,
   "Turnovers": 2,
   "PersonalFouls": 4,
   "Points": 37,
   "GameScore": 23.3,
   "+": {
      "-": -1
   }
},
{
   "Rank": 1,
   "SeasonGame": 1,
   "Date": "2004-04-17 (P)",
   "Age": "25-238",
   "Team": "LAL",
   "FIELD6": "",
   "Opponent": "HOU",
   "FIELD8": "W (+1)",
   "GamesStarted": 1,
   "MinsPlayed": "43:21:00",
   "FieldGoals": 4,
   "FieldGoalsAttempted": 19,
   "FieldGoalPercentage": 0.211,
   "ThreePointFieldGoals": 1,
   "ThreePointFieldGoalAttempted": 4,
   "ThreePointFieldGoalPercentage": 0.25,
   "FreeThrows": 7,
   "FreeThrowAttempts": 8,
   "FreeThrowPercentage": 0.875,
   "OffensiveRebounds": 1,
   "DeffensiveRebounds": 4,
   "TotalRebounds": 5,
   "Assists": 6,
   "Steals": 5,
   "Blocks": 0,
   "Turnovers": 0,
   "PersonalFouls": 2,
   "Points": 16,
   "GameScore": 14.2,
   "+": {
      "-": 2
   }
},
{
   "Rank": 2,
   "SeasonGame": 2,
   "Date": "2004-04-19 (P)",
   "Age": "25-240",
   "Team": "LAL",
   "FIELD6": "",
   "Opponent": "HOU",
   "FIELD8": "W (+14)",
   "GamesStarted": 1,
   "MinsPlayed": "45:09:00",
   "FieldGoals": 9,
   "FieldGoalsAttempted": 20,
   "FieldGoalPercentage": 0.45,
   "ThreePointFieldGoals": 2,
   "ThreePointFieldGoalAttempted": 6,
   "ThreePointFieldGoalPercentage": 0.333,
   "FreeThrows": 16,
   "FreeThrowAttempts": 17,
   "FreeThrowPercentage": 0.941,
   "OffensiveRebounds": 0,
   "DeffensiveRebounds": 4,
   "TotalRebounds": 4,
   "Assists": 4,
   "Steals": 1,
   "Blocks": 0,
   "Turnovers": 1,
   "PersonalFouls": 3,
   "Points": 36,
   "GameScore": 28,
   "+": {
      "-": 17
   }
},
{
   "Rank": 3,
   "SeasonGame": 3,
   "Date": "2004-04-23 (P)",
   "Age": "25-244",
   "Team": "LAL",
   "FIELD6": "@",
   "Opponent": "HOU",
   "FIELD8": "L (-11)",
   "GamesStarted": 1,
   "MinsPlayed": "42:57:00",
   "FieldGoals": 7,
   "FieldGoalsAttempted": 20,
   "FieldGoalPercentage": 0.35,
   "ThreePointFieldGoals": 0,
   "ThreePointFieldGoalAttempted": 3,
   "ThreePointFieldGoalPercentage": 0,
   "FreeThrows": 7,
   "FreeThrowAttempts": 8,
   "FreeThrowPercentage": 0.875,
   "OffensiveRebounds": 3,
   "DeffensiveRebounds": 4,
   "TotalRebounds": 7,
   "Assists": 6,
   "Steals": 3,
   "Blocks": 1,
   "Turnovers": 1,
   "PersonalFouls": 4,
   "Points": 21,
   "GameScore": 18,
   "+": {
      "-": -12
   }
},
{
   "Rank": 4,
   "SeasonGame": 4,
   "Date": "2004-04-25 (P)",
   "Age": "25-246",
   "Team": "LAL",
   "FIELD6": "@",
   "Opponent": "HOU",
   "FIELD8": "W (+4)",
   "GamesStarted": 1,
   "MinsPlayed": "50:14:00",
   "FieldGoals": 7,
   "FieldGoalsAttempted": 21,
   "FieldGoalPercentage": 0.333,
   "ThreePointFieldGoals": 0,
   "ThreePointFieldGoalAttempted": 2,
   "ThreePointFieldGoalPercentage": 0,
   "FreeThrows": 4,
   "FreeThrowAttempts": 5,
   "FreeThrowPercentage": 0.8,
   "OffensiveRebounds": 2,
   "DeffensiveRebounds": 4,
   "TotalRebounds": 6,
   "Assists": 5,
   "Steals": 2,
   "Blocks": 0,
   "Turnovers": 3,
   "PersonalFouls": 4,
   "Points": 18,
   "GameScore": 9.2,
   "+": {
      "-": -1
   }
},
{
   "Rank": 5,
   "SeasonGame": 5,
   "Date": "2004-04-28 (P)",
   "Age": "25-249",
   "Team": "LAL",
   "FIELD6": "",
   "Opponent": "HOU",
   "FIELD8": "W (+19)",
   "GamesStarted": 1,
   "MinsPlayed": "40:53:00",
   "FieldGoals": 12,
   "FieldGoalsAttempted": 21,
   "FieldGoalPercentage": 0.571,
   "ThreePointFieldGoals": 1,
   "ThreePointFieldGoalAttempted": 4,
   "ThreePointFieldGoalPercentage": 0.25,
   "FreeThrows": 6,
   "FreeThrowAttempts": 6,
   "FreeThrowPercentage": 1,
   "OffensiveRebounds": 1,
   "DeffensiveRebounds": 5,
   "TotalRebounds": 6,
   "Assists": 10,
   "Steals": 3,
   "Blocks": 0,
   "Turnovers": 1,
   "PersonalFouls": 3,
   "Points": 31,
   "GameScore": 31.1,
   "+": {
      "-": 23
   }
},
{
   "Rank": 6,
   "SeasonGame": 6,
   "Date": "2004-05-02 (P)",
   "Age": "25-253",
   "Team": "LAL",
   "FIELD6": "@",
   "Opponent": "SAS",
   "FIELD8": "L (-10)",
   "GamesStarted": 1,
   "MinsPlayed": "44:35:00",
   "FieldGoals": 10,
   "FieldGoalsAttempted": 26,
   "FieldGoalPercentage": 0.385,
   "ThreePointFieldGoals": 2,
   "ThreePointFieldGoalAttempted": 6,
   "ThreePointFieldGoalPercentage": 0.333,
   "FreeThrows": 9,
   "FreeThrowAttempts": 10,
   "FreeThrowPercentage": 0.9,
   "OffensiveRebounds": 2,
   "DeffensiveRebounds": 8,
   "TotalRebounds": 10,
   "Assists": 4,
   "Steals": 2,
   "Blocks": 0,
   "Turnovers": 4,
   "PersonalFouls": 1,
   "Points": 31,
   "GameScore": 20.6,
   "+": {
      "-": -7
   }
},
{
   "Rank": 7,
   "SeasonGame": 7,
   "Date": "2004-05-05 (P)",
   "Age": "25-256",
   "Team": "LAL",
   "FIELD6": "@",
   "Opponent": "SAS",
   "FIELD8": "L (-10)",
   "GamesStarted": 1,
   "MinsPlayed": "42:19:00",
   "FieldGoals": 7,
   "FieldGoalsAttempted": 17,
   "FieldGoalPercentage": 0.412,
   "ThreePointFieldGoals": 0,
   "ThreePointFieldGoalAttempted": 1,
   "ThreePointFieldGoalPercentage": 0,
   "FreeThrows": 1,
   "FreeThrowAttempts": 2,
   "FreeThrowPercentage": 0.5,
   "OffensiveRebounds": 2,
   "DeffensiveRebounds": 3,
   "TotalRebounds": 5,
   "Assists": 8,
   "Steals": 1,
   "Blocks": 0,
   "Turnovers": 2,
   "PersonalFouls": 4,
   "Points": 15,
   "GameScore": 10.8,
   "+": {
      "-": -8
   }
},
{
   "Rank": 8,
   "SeasonGame": 8,
   "Date": "2004-05-09 (P)",
   "Age": "25-260",
   "Team": "LAL",
   "FIELD6": "",
   "Opponent": "SAS",
   "FIELD8": "W (+24)",
   "GamesStarted": 1,
   "MinsPlayed": "41:27:00",
   "FieldGoals": 7,
   "FieldGoalsAttempted": 13,
   "FieldGoalPercentage": 0.538,
   "ThreePointFieldGoals": 4,
   "ThreePointFieldGoalAttempted": 7,
   "ThreePointFieldGoalPercentage": 0.571,
   "FreeThrows": 4,
   "FreeThrowAttempts": 8,
   "FreeThrowPercentage": 0.5,
   "OffensiveRebounds": 0,
   "DeffensiveRebounds": 6,
   "TotalRebounds": 6,
   "Assists": 6,
   "Steals": 2,
   "Blocks": 0,
   "Turnovers": 5,
   "PersonalFouls": 3,
   "Points": 22,
   "GameScore": 15.9,
   "+": {
      "-": 31
   }
},
{
   "Rank": 9,
   "SeasonGame": 9,
   "Date": "2004-05-11 (P)",
   "Age": "25-262",
   "Team": "LAL",
   "FIELD6": "",
   "Opponent": "SAS",
   "FIELD8": "W (+8)",
   "GamesStarted": 1,
   "MinsPlayed": "44:33:00",
   "FieldGoals": 15,
   "FieldGoalsAttempted": 27,
   "FieldGoalPercentage": 0.556,
   "ThreePointFieldGoals": 2,
   "ThreePointFieldGoalAttempted": 4,
   "ThreePointFieldGoalPercentage": 0.5,
   "FreeThrows": 10,
   "FreeThrowAttempts": 13,
   "FreeThrowPercentage": 0.769,
   "OffensiveRebounds": 0,
   "DeffensiveRebounds": 6,
   "TotalRebounds": 6,
   "Assists": 5,
   "Steals": 3,
   "Blocks": 1,
   "Turnovers": 0,
   "PersonalFouls": 2,
   "Points": 42,
   "GameScore": 36.1,
   "+": {
      "-": 10
   }
},
{
   "Rank": 10,
   "SeasonGame": 10,
   "Date": "2004-05-13 (P)",
   "Age": "25-264",
   "Team": "LAL",
   "FIELD6": "@",
   "Opponent": "SAS",
   "FIELD8": "W (+1)",
   "GamesStarted": 1,
   "MinsPlayed": "46:53:00",
   "FieldGoals": 11,
   "FieldGoalsAttempted": 27,
   "FieldGoalPercentage": 0.407,
   "ThreePointFieldGoals": 0,
   "ThreePointFieldGoalAttempted": 4,
   "ThreePointFieldGoalPercentage": 0,
   "FreeThrows": 0,
   "FreeThrowAttempts": 0,
   "FreeThrowPercentage": null,
   "OffensiveRebounds": 0,
   "DeffensiveRebounds": 4,
   "TotalRebounds": 4,
   "Assists": 5,
   "Steals": 1,
   "Blocks": 0,
   "Turnovers": 5,
   "PersonalFouls": 1,
   "Points": 22,
   "GameScore": 7.8,
   "+": {
      "-": 0
   }
},
{
   "Rank": 11,
   "SeasonGame": 11,
   "Date": "2004-05-15 (P)",
   "Age": "25-266",
   "Team": "LAL",
   "FIELD6": "",
   "Opponent": "SAS",
   "FIELD8": "W (+12)",
   "GamesStarted": 1,
   "MinsPlayed": "43:59:00",
   "FieldGoals": 10,
   "FieldGoalsAttempted": 20,
   "FieldGoalPercentage": 0.5,
   "ThreePointFieldGoals": 0,
   "ThreePointFieldGoalAttempted": 3,
   "ThreePointFieldGoalPercentage": 0,
   "FreeThrows": 6,
   "FreeThrowAttempts": 8,
   "FreeThrowPercentage": 0.75,
   "OffensiveRebounds": 0,
   "DeffensiveRebounds": 7,
   "TotalRebounds": 7,
   "Assists": 7,
   "Steals": 1,
   "Blocks": 0,
   "Turnovers": 4,
   "PersonalFouls": 2,
   "Points": 26,
   "GameScore": 18.4,
   "+": {
      "-": 11
   }
},
{
   "Rank": 12,
   "SeasonGame": 12,
   "Date": "2004-05-21 (P)",
   "Age": "25-272",
   "Team": "LAL",
   "FIELD6": "@",
   "Opponent": "MIN",
   "FIELD8": "W (+9)",
   "GamesStarted": 1,
   "MinsPlayed": "44:29:00",
   "FieldGoals": 9,
   "FieldGoalsAttempted": 20,
   "FieldGoalPercentage": 0.45,
   "ThreePointFieldGoals": 0,
   "ThreePointFieldGoalAttempted": 1,
   "ThreePointFieldGoalPercentage": 0,
   "FreeThrows": 5,
   "FreeThrowAttempts": 8,
   "FreeThrowPercentage": 0.625,
   "OffensiveRebounds": 0,
   "DeffensiveRebounds": 3,
   "TotalRebounds": 3,
   "Assists": 6,
   "Steals": 3,
   "Blocks": 0,
   "Turnovers": 3,
   "PersonalFouls": 2,
   "Points": 23,
   "GameScore": 15.7,
   "+": {
      "-": 8
   }
},
{
   "Rank": 13,
   "SeasonGame": 13,
   "Date": "2004-05-23 (P)",
   "Age": "25-274",
   "Team": "LAL",
   "FIELD6": "@",
   "Opponent": "MIN",
   "FIELD8": "L (-18)",
   "GamesStarted": 1,
   "MinsPlayed": "41:16:00",
   "FieldGoals": 10,
   "FieldGoalsAttempted": 24,
   "FieldGoalPercentage": 0.417,
   "ThreePointFieldGoals": 0,
   "ThreePointFieldGoalAttempted": 4,
   "ThreePointFieldGoalPercentage": 0,
   "FreeThrows": 7,
   "FreeThrowAttempts": 10,
   "FreeThrowPercentage": 0.7,
   "OffensiveRebounds": 2,
   "DeffensiveRebounds": 3,
   "TotalRebounds": 5,
   "Assists": 6,
   "Steals": 2,
   "Blocks": 0,
   "Turnovers": 2,
   "PersonalFouls": 1,
   "Points": 27,
   "GameScore": 19.1,
   "+": {
      "-": -16
   }
},
{
   "Rank": 14,
   "SeasonGame": 14,
   "Date": "2004-05-25 (P)",
   "Age": "25-276",
   "Team": "LAL",
   "FIELD6": "",
   "Opponent": "MIN",
   "FIELD8": "W (+11)",
   "GamesStarted": 1,
   "MinsPlayed": "44:51:00",
   "FieldGoals": 5,
   "FieldGoalsAttempted": 12,
   "FieldGoalPercentage": 0.417,
   "ThreePointFieldGoals": 2,
   "ThreePointFieldGoalAttempted": 6,
   "ThreePointFieldGoalPercentage": 0.333,
   "FreeThrows": 10,
   "FreeThrowAttempts": 11,
   "FreeThrowPercentage": 0.909,
   "OffensiveRebounds": 0,
   "DeffensiveRebounds": 2,
   "TotalRebounds": 2,
   "Assists": 6,
   "Steals": 0,
   "Blocks": 0,
   "Turnovers": 4,
   "PersonalFouls": 3,
   "Points": 22,
   "GameScore": 14.8,
   "+": {
      "-": 11
   }
},
{
   "Rank": 15,
   "SeasonGame": 15,
   "Date": "2004-05-27 (P)",
   "Age": "25-278",
   "Team": "LAL",
   "FIELD6": "",
   "Opponent": "MIN",
   "FIELD8": "W (+7)",
   "GamesStarted": 1,
   "MinsPlayed": "40:39:00",
   "FieldGoals": 10,
   "FieldGoalsAttempted": 24,
   "FieldGoalPercentage": 0.417,
   "ThreePointFieldGoals": 2,
   "ThreePointFieldGoalAttempted": 8,
   "ThreePointFieldGoalPercentage": 0.25,
   "FreeThrows": 9,
   "FreeThrowAttempts": 10,
   "FreeThrowPercentage": 0.9,
   "OffensiveRebounds": 2,
   "DeffensiveRebounds": 6,
   "TotalRebounds": 8,
   "Assists": 4,
   "Steals": 1,
   "Blocks": 1,
   "Turnovers": 4,
   "PersonalFouls": 3,
   "Points": 31,
   "GameScore": 20.3,
   "+": {
      "-": 4
   }
},
{
   "Rank": 16,
   "SeasonGame": 16,
   "Date": "2004-05-29 (P)",
   "Age": "25-280",
   "Team": "LAL",
   "FIELD6": "@",
   "Opponent": "MIN",
   "FIELD8": "L (-2)",
   "GamesStarted": 1,
   "MinsPlayed": "44:16:00",
   "FieldGoals": 8,
   "FieldGoalsAttempted": 19,
   "FieldGoalPercentage": 0.421,
   "ThreePointFieldGoals": 3,
   "ThreePointFieldGoalAttempted": 8,
   "ThreePointFieldGoalPercentage": 0.375,
   "FreeThrows": 4,
   "FreeThrowAttempts": 6,
   "FreeThrowPercentage": 0.667,
   "OffensiveRebounds": 1,
   "DeffensiveRebounds": 5,
   "TotalRebounds": 6,
   "Assists": 7,
   "Steals": 1,
   "Blocks": 0,
   "Turnovers": 4,
   "PersonalFouls": 3,
   "Points": 23,
   "GameScore": 15,
   "+": {
      "-": -1
   }
},
{
   "Rank": 17,
   "SeasonGame": 17,
   "Date": "2004-05-31 (P)",
   "Age": "25-282",
   "Team": "LAL",
   "FIELD6": "",
   "Opponent": "MIN",
   "FIELD8": "W (+6)",
   "GamesStarted": 1,
   "MinsPlayed": "39:12:00",
   "FieldGoals": 6,
   "FieldGoalsAttempted": 17,
   "FieldGoalPercentage": 0.353,
   "ThreePointFieldGoals": 1,
   "ThreePointFieldGoalAttempted": 3,
   "ThreePointFieldGoalPercentage": 0.333,
   "FreeThrows": 7,
   "FreeThrowAttempts": 11,
   "FreeThrowPercentage": 0.636,
   "OffensiveRebounds": 0,
   "DeffensiveRebounds": 0,
   "TotalRebounds": 0,
   "Assists": 4,
   "Steals": 2,
   "Blocks": 1,
   "Turnovers": 0,
   "PersonalFouls": 3,
   "Points": 20,
   "GameScore": 13.2,
   "+": {
      "-": 10
   }
},
{
   "Rank": 18,
   "SeasonGame": 18,
   "Date": "2004-06-06 (P)",
   "Age": "25-288",
   "Team": "LAL",
   "FIELD6": "",
   "Opponent": "DET",
   "FIELD8": "L (-12)",
   "GamesStarted": 1,
   "MinsPlayed": "47:14:00",
   "FieldGoals": 10,
   "FieldGoalsAttempted": 27,
   "FieldGoalPercentage": 0.37,
   "ThreePointFieldGoals": 1,
   "ThreePointFieldGoalAttempted": 6,
   "ThreePointFieldGoalPercentage": 0.167,
   "FreeThrows": 4,
   "FreeThrowAttempts": 4,
   "FreeThrowPercentage": 1,
   "OffensiveRebounds": 1,
   "DeffensiveRebounds": 3,
   "TotalRebounds": 4,
   "Assists": 4,
   "Steals": 4,
   "Blocks": 2,
   "Turnovers": 3,
   "PersonalFouls": 2,
   "Points": 25,
   "GameScore": 16.1,
   "+": {
      "-": -12
   }
},
{
   "Rank": 19,
   "SeasonGame": 19,
   "Date": "2004-06-08 (P)",
   "Age": "25-290",
   "Team": "LAL",
   "FIELD6": "",
   "Opponent": "DET",
   "FIELD8": "W (+8)",
   "GamesStarted": 1,
   "MinsPlayed": "48:44:00",
   "FieldGoals": 14,
   "FieldGoalsAttempted": 27,
   "FieldGoalPercentage": 0.519,
   "ThreePointFieldGoals": 1,
   "ThreePointFieldGoalAttempted": 5,
   "ThreePointFieldGoalPercentage": 0.2,
   "FreeThrows": 4,
   "FreeThrowAttempts": 5,
   "FreeThrowPercentage": 0.8,
   "OffensiveRebounds": 0,
   "DeffensiveRebounds": 4,
   "TotalRebounds": 4,
   "Assists": 7,
   "Steals": 2,
   "Blocks": 0,
   "Turnovers": 5,
   "PersonalFouls": 5,
   "Points": 33,
   "GameScore": 20.4,
   "+": {
      "-": 7
   }
},
{
   "Rank": 20,
   "SeasonGame": 20,
   "Date": "2004-06-10 (P)",
   "Age": "25-292",
   "Team": "LAL",
   "FIELD6": "@",
   "Opponent": "DET",
   "FIELD8": "L (-20)",
   "GamesStarted": 1,
   "MinsPlayed": "44:42:00",
   "FieldGoals": 4,
   "FieldGoalsAttempted": 13,
   "FieldGoalPercentage": 0.308,
   "ThreePointFieldGoals": 0,
   "ThreePointFieldGoalAttempted": 4,
   "ThreePointFieldGoalPercentage": 0,
   "FreeThrows": 3,
   "FreeThrowAttempts": 3,
   "FreeThrowPercentage": 1,
   "OffensiveRebounds": 0,
   "DeffensiveRebounds": 3,
   "TotalRebounds": 3,
   "Assists": 5,
   "Steals": 1,
   "Blocks": 1,
   "Turnovers": 4,
   "PersonalFouls": 3,
   "Points": 11,
   "GameScore": 4.4,
   "+": {
      "-": -20
   }
},
{
   "Rank": 21,
   "SeasonGame": 21,
   "Date": "2004-06-13 (P)",
   "Age": "25-295",
   "Team": "LAL",
   "FIELD6": "@",
   "Opponent": "DET",
   "FIELD8": "L (-8)",
   "GamesStarted": 1,
   "MinsPlayed": "44:46:00",
   "FieldGoals": 8,
   "FieldGoalsAttempted": 25,
   "FieldGoalPercentage": 0.32,
   "ThreePointFieldGoals": 2,
   "ThreePointFieldGoalAttempted": 6,
   "ThreePointFieldGoalPercentage": 0.333,
   "FreeThrows": 2,
   "FreeThrowAttempts": 2,
   "FreeThrowPercentage": 1,
   "OffensiveRebounds": 0,
   "DeffensiveRebounds": 0,
   "TotalRebounds": 0,
   "Assists": 2,
   "Steals": 1,
   "Blocks": 0,
   "Turnovers": 3,
   "PersonalFouls": 3,
   "Points": 20,
   "GameScore": 3.9,
   "+": {
      "-": -8
   }
},
{
   "Rank": 22,
   "SeasonGame": 22,
   "Date": "2004-06-15 (P)",
   "Age": "25-297",
   "Team": "LAL",
   "FIELD6": "@",
   "Opponent": "DET",
   "FIELD8": "L (-13)",
   "GamesStarted": 1,
   "MinsPlayed": "45:34:00",
   "FieldGoals": 7,
   "FieldGoalsAttempted": 21,
   "FieldGoalPercentage": 0.333,
   "ThreePointFieldGoals": 0,
   "ThreePointFieldGoalAttempted": 2,
   "ThreePointFieldGoalPercentage": 0,
   "FreeThrows": 10,
   "FreeThrowAttempts": 11,
   "FreeThrowPercentage": 0.909,
   "OffensiveRebounds": 1,
   "DeffensiveRebounds": 2,
   "TotalRebounds": 3,
   "Assists": 4,
   "Steals": 1,
   "Blocks": 0,
   "Turnovers": 3,
   "PersonalFouls": 2,
   "Points": 24,
   "GameScore": 13,
   "+": {
      "-": -19
   }
}
]